skia.cpython-311-darwin.so
skia_python-138.0.dist-info/RECORD
skia_python-138.0.dist-info/WHEEL
skia_python-138.0.dist-info/top_level.txt
skia_python-138.0.dist-info/METADATA
skia_python-138.0.dist-info/licenses/LICENSE
